svsa/__init__.py
svsa/crbs6.py
svsa/crbs7.py
svsa/gen_spectra.py
svsa/support_vector_spectrum.py
svsa-0.0.6.dist-info/LICENSE
svsa-0.0.6.dist-info/METADATA
svsa-0.0.6.dist-info/WHEEL
svsa-0.0.6.dist-info/top_level.txt
svsa-0.0.6.dist-info/zip-safe
svsa-0.0.6.dist-info/RECORD
